edt.cpython-39-x86_64-linux-gnu.so
edt-3.0.0.dist-info/pbr.json
edt-3.0.0.dist-info/WHEEL
edt-3.0.0.dist-info/RECORD
edt-3.0.0.dist-info/top_level.txt
edt-3.0.0.dist-info/METADATA
